muacryptcc/__init__.py
muacryptcc/commands.py
muacryptcc/filestore.py
muacryptcc/plugin.py
muacryptcc-0.8.0.dist-info/METADATA
muacryptcc-0.8.0.dist-info/RECORD
muacryptcc-0.8.0.dist-info/WHEEL
muacryptcc-0.8.0.dist-info/entry_points.txt
muacryptcc-0.8.0.dist-info/top_level.txt
