Metadata-Version: 2.1
Name: muacryptcc
Version: 0.8.0
Summary: UNKNOWN
Home-page: https://muacryptcc.readthedocs.io
Author: UNKNOWN
Author-email: UNKNOWN
License: MIT license
Platform: unix
Platform: linux
Platform: osx
Platform: cygwin
Platform: win32
Classifier: Development Status :: 3 - Alpha
Classifier: Intended Audience :: Developers
Classifier: License :: OSI Approved :: MIT License
Classifier: Operating System :: POSIX
Classifier: Operating System :: MacOS :: MacOS X
Classifier: Topic :: Utilities
Classifier: Intended Audience :: Developers
Classifier: Programming Language :: Python
Requires-Dist: base58
Requires-Dist: muacrypt
